jirapy/__init__.py
jirapy/jirapy.py
jirapy-0.1.dist-info/DESCRIPTION.rst
jirapy-0.1.dist-info/LICENSE.txt
jirapy-0.1.dist-info/METADATA
jirapy-0.1.dist-info/RECORD
jirapy-0.1.dist-info/WHEEL
jirapy-0.1.dist-info/metadata.json
jirapy-0.1.dist-info/top_level.txt
