Metadata-Version: 2.0
Name: jirapy
Version: 0.1
Summary: JIRA Data Wrapper for Easy WebHook Handling
Home-page: https://github.com/Neko-Design/jirapy
Author: Ewen McCahon
Author-email: ewen.m.mccahon@student.uts.edu.au
License: APACHE2
Keywords: jira,api,wrapper,interface,webhooks,comments
Platform: UNKNOWN
Requires-Dist: requests
